cnmfsns/__init__.py
cnmfsns/cli.py
cnmfsns/cnmf.py
cnmfsns/colors.py
cnmfsns/config.py
cnmfsns/dataset.py
cnmfsns/integration.py
cnmfsns/nancorrmp.py
cnmfsns/plots.py
cnmfsns/sns.py
cnmfsns/utils.py
cnmfsns-1.8.2.dist-info/LICENSE
cnmfsns-1.8.2.dist-info/METADATA
cnmfsns-1.8.2.dist-info/WHEEL
cnmfsns-1.8.2.dist-info/entry_points.txt
cnmfsns-1.8.2.dist-info/top_level.txt
cnmfsns-1.8.2.dist-info/RECORD
