Metadata-Version: 2.1
Name: cnmfsns
Version: 1.8.2
Summary: cNMF Solution Network Space
Home-page: https://github.com/MorrissyLab/cNMF-SNS
Author: Ted Verhey
Author-email: tbverhey@ucalgary.ca
Project-URL: Bug Tracker, https://github.com/MorrissyLab/cNMF-SNS/issues
Classifier: Programming Language :: Python :: 3
Classifier: License :: OSI Approved :: MIT License
Classifier: Operating System :: OS Independent
Requires-Python: >=3.9
License-File: LICENSE
Requires-Dist: anndata >=0.8.0
Requires-Dist: seaborn
Requires-Dist: statsmodels
Requires-Dist: networkx
Requires-Dist: pandas
Requires-Dist: numpy
Requires-Dist: scipy >=1.9.0
Requires-Dist: matplotlib
Requires-Dist: upsetplot
Requires-Dist: httplib2
Requires-Dist: tomli
Requires-Dist: tomli-w
Requires-Dist: distinctipy
Requires-Dist: click
Requires-Dist: pygraphviz
Requires-Dist: igraph
Requires-Dist: pyyaml
Requires-Dist: scikit-learn
Requires-Dist: fastcluster
Requires-Dist: scanpy
